{
  "version": "2.0",
  "created": "2026-02-25T18:02:32.519024",
  "steps": [
    {
      "name": "Step_5",
      "poses": [
        {
          "name": "Pose_1",
          "timestamp": "2026-02-25T16:17:45.882212",
          "arm": "both",
          "pose_type": "joint",
          "joints": [
            -0.002877088578621567,
            0.01553627832455895,
            -0.0009590295262071891,
            -0.022441290913253198,
            -0.0005754177157246687,
            -0.0005754177157246687,
            -0.0005754177157246687
          ],
          "position": {
            "x": -0.0038691010889512593,
            "y": 0.2060259541872585,
            "z": -0.5794522568142493
          },
          "euler": {
            "x": -0.014983310224968816,
            "y": 0.025867169077498083,
            "z": -0.0018921894807548611
          },
          "speed": 0.3,
          "acceleration": 0.5,
          "hand_positions": [
            255,
            255,
            255,
            255,
            255,
            255
          ],
          "hand_type": null,
          "hand_side": null,
          "force_grab": null,
          "trajectory_file": null,
          "trajectory_duration": null,
          "trajectory_points": null,
          "right_joints": [
            -0.00019180590524214836,
            -0.00019180590524214836,
            -0.00019180590524214836,
            -0.00019180590524214836,
            -0.00019180590524214836,
            -0.00019180590524214836,
            -0.00019180590524214836
          ],
          "right_position": {
            "x": 0.004944302060432077,
            "y": -0.2148807177010635,
            "z": -0.5794972143347326
          },
          "right_euler": {
            "x": 0.0003837221931204833,
            "y": -0.0005753441120131288,
            "z": -0.00038368542830373366
          },
          "right_speed": 0.3,
          "right_acceleration": 0.5,
          "right_hand_positions": [
            255,
            255,
            255,
            255,
            255,
            255
          ],
          "right_hand_type": null,
          "gripper_position": 0,
          "gripper_torque": 50
        },
        {
          "name": "Pose_2",
          "timestamp": "2026-02-25T16:18:22.882203",
          "arm": "both",
          "pose_type": "joint",
          "joints": [
            -0.002877088578621567,
            0.01553627832455895,
            -0.0009590295262071891,
            -0.022441290913253198,
            -0.0005754177157246687,
            -0.0005754177157246687,
            -0.0005754177157246687
          ],
          "position": {
            "x": -0.0038691010889512593,
            "y": 0.2060259541872585,
            "z": -0.5794522568142493
          },
          "euler": {
            "x": -0.014983310224968816,
            "y": 0.025867169077498083,
            "z": -0.0018921894807548611
          },
          "speed": 0.3,
          "acceleration": 0.5,
          "hand_positions": [
            255,
            255,
            255,
            255,
            255,
            255
          ],
          "hand_type": null,
          "hand_side": null,
          "force_grab": null,
          "trajectory_file": null,
          "trajectory_duration": null,
          "trajectory_points": null,
          "right_joints": [
            0.3550327306019678,
            0.03970382238498438,
            -0.170899061570152,
            -0.5537436484321354,
            0.04469077592126247,
            -0.16898100251773762,
            -0.0005754177157246687
          ],
          "right_position": {
            "x": -0.011151001990033771,
            "y": -0.2652953221800149,
            "z": -0.5464101363096472
          },
          "right_euler": {
            "x": -0.11228452692255739,
            "y": -0.3715894945860657,
            "z": -0.061978826931675744
          },
          "right_speed": 0.3,
          "right_acceleration": 0.5,
          "right_hand_positions": [
            255,
            255,
            255,
            255,
            255,
            255
          ],
          "right_hand_type": null,
          "gripper_position": 0,
          "gripper_torque": 50
        },
        {
          "name": "Pose_3",
          "timestamp": "2026-02-25T16:18:45.106571",
          "arm": "both",
          "pose_type": "joint",
          "joints": [
            -0.002877088578621567,
            0.01553627832455895,
            -0.0009590295262071891,
            -0.022441290913253198,
            -0.0005754177157246687,
            -0.0005754177157246687,
            -0.0005754177157246687
          ],
          "position": {
            "x": -0.0038691010889512593,
            "y": 0.2060259541872585,
            "z": -0.5794522568142493
          },
          "euler": {
            "x": -0.014983310224968816,
            "y": 0.025867169077498083,
            "z": -0.0018921894807548611
          },
          "speed": 0.3,
          "acceleration": 0.5,
          "hand_positions": [
            255,
            255,
            255,
            255,
            255,
            255
          ],
          "hand_type": null,
          "hand_side": null,
          "force_grab": null,
          "trajectory_file": null,
          "trajectory_duration": null,
          "trajectory_points": null,
          "right_joints": [
            0.579829251544977,
            0.13905928130006906,
            -0.19545021744106172,
            -1.028655069810025,
            -0.048526894026093004,
            -0.29634012359807826,
            -0.0009590295262071891
          ],
          "right_position": {
            "x": 0.019453815250676854,
            "y": -0.3247257768654608,
            "z": -0.4674811075847341
          },
          "right_euler": {
            "x": -0.2758869167866237,
            "y": -0.7587197587304845,
            "z": 0.05866706095006353
          },
          "right_speed": 0.3,
          "right_acceleration": 0.5,
          "right_hand_positions": [
            255,
            255,
            255,
            255,
            255,
            255
          ],
          "right_hand_type": null,
          "gripper_position": 0,
          "gripper_torque": 50
        },
        {
          "name": "Pose_4",
          "timestamp": "2026-02-25T16:19:06.594745",
          "arm": "both",
          "pose_type": "joint",
          "joints": [
            -0.002877088578621567,
            0.01553627832455895,
            -0.0009590295262071891,
            -0.022441290913253198,
            -0.0005754177157246687,
            -0.0005754177157246687,
            -0.0005754177157246687
          ],
          "position": {
            "x": -0.0038691010889512593,
            "y": 0.2060259541872585,
            "z": -0.5794522568142493
          },
          "euler": {
            "x": -0.014983310224968816,
            "y": 0.025867169077498083,
            "z": -0.0018921894807548611
          },
          "speed": 0.3,
          "acceleration": 0.5,
          "hand_positions": [
            255,
            255,
            255,
            255,
            255,
            255
          ],
          "hand_type": null,
          "hand_side": null,
          "force_grab": null,
          "trajectory_file": null,
          "trajectory_duration": null,
          "trajectory_points": null,
          "right_joints": [
            0.8356983291371023,
            0.170899061570152,
            -0.16437766079194205,
            -1.0650981918059053,
            -0.05197940032043924,
            -0.633151293202106,
            -0.0009590295262071891
          ],
          "right_position": {
            "x": -0.05523829185829464,
            "y": -0.32215598115211913,
            "z": -0.42456260741354146
          },
          "right_euler": {
            "x": -0.3440549159206764,
            "y": -0.8567438755641023,
            "z": 0.22856886475497593
          },
          "right_speed": 0.3,
          "right_acceleration": 0.5,
          "right_hand_positions": [
            255,
            255,
            255,
            255,
            255,
            255
          ],
          "right_hand_type": null,
          "gripper_position": 0,
          "gripper_torque": 50
        },
        {
          "name": "Pose_5",
          "timestamp": "2026-02-25T16:19:35.938417",
          "arm": "both",
          "pose_type": "joint",
          "joints": [
            -0.002877088578621567,
            0.01553627832455895,
            -0.0009590295262071891,
            -0.022441290913253198,
            -0.0005754177157246687,
            -0.0005754177157246687,
            -0.0005754177157246687
          ],
          "position": {
            "x": -0.0038691010889512593,
            "y": 0.2060259541872585,
            "z": -0.5794522568142493
          },
          "euler": {
            "x": -0.014983310224968816,
            "y": 0.025867169077498083,
            "z": -0.0018921894807548611
          },
          "speed": 0.3,
          "acceleration": 0.5,
          "hand_positions": [
            255,
            255,
            255,
            255,
            255,
            255
          ],
          "hand_type": null,
          "hand_side": null,
          "force_grab": null,
          "trajectory_file": null,
          "trajectory_duration": null,
          "trajectory_points": null,
          "right_joints": [
            0.6262462806134135,
            0.09686198214694386,
            -0.404518654154268,
            -1.7494616617074836,
            -0.18202380407415752,
            -0.21961776150148893,
            -0.18624353398947058
          ],
          "right_position": {
            "x": 0.11520708722588963,
            "y": -0.34362334519731075,
            "z": -0.2993296023035055
          },
          "right_euler": {
            "x": -0.5676217746673883,
            "y": -1.3682156585700487,
            "z": 0.3914314669195498
          },
          "right_speed": 0.3,
          "right_acceleration": 0.5,
          "right_hand_positions": [
            255,
            255,
            255,
            255,
            255,
            255
          ],
          "right_hand_type": null,
          "gripper_position": 0,
          "gripper_torque": 50
        },
        {
          "name": "Pose_6",
          "timestamp": "2026-02-25T16:22:59.735089",
          "arm": "both",
          "pose_type": "joint",
          "joints": [
            -0.002877088578621567,
            0.01553627832455895,
            -0.0009590295262071891,
            -0.022441290913253198,
            -0.0005754177157246687,
            -0.0005754177157246687,
            -0.0005754177157246687
          ],
          "position": {
            "x": -0.0038691010889512593,
            "y": 0.2060259541872585,
            "z": -0.5794522568142493
          },
          "euler": {
            "x": -0.014983310224968816,
            "y": 0.025867169077498083,
            "z": -0.0018921894807548611
          },
          "speed": 0.3,
          "acceleration": 0.5,
          "hand_positions": [
            255,
            255,
            255,
            255,
            255,
            255
          ],
          "hand_type": null,
          "hand_side": null,
          "force_grab": null,
          "trajectory_file": null,
          "trajectory_duration": null,
          "trajectory_points": null,
          "right_joints": [
            0.134839551384756,
            0.11489173723964186,
            -0.4118072785534448,
            -1.1901556420233455,
            -0.025126573586632617,
            -0.36078690775921274,
            -0.26987090867475416
          ],
          "right_position": {
            "x": 0.22674208661757445,
            "y": -0.35823413003481475,
            "z": -0.3565383361240742
          },
          "right_euler": {
            "x": -0.6852105154727746,
            "y": -1.4038901577708276,
            "z": 0.5394456925498832
          },
          "right_speed": 0.3,
          "right_acceleration": 0.5,
          "right_hand_positions": [
            255,
            255,
            255,
            255,
            255,
            255
          ],
          "right_hand_type": null,
          "gripper_position": 0,
          "gripper_torque": 50
        },
        {
          "name": "Pose_8",
          "timestamp": "2026-02-25T16:24:39.347057",
          "arm": "both",
          "pose_type": "joint",
          "joints": [
            -0.002877088578621567,
            0.01553627832455895,
            -0.0009590295262071891,
            -0.022441290913253198,
            -0.0005754177157246687,
            -0.0005754177157246687,
            -0.0005754177157246687
          ],
          "position": {
            "x": -0.0038691010889512593,
            "y": 0.2060259541872585,
            "z": -0.5794522568142493
          },
          "euler": {
            "x": -0.014983310224968816,
            "y": 0.025867169077498083,
            "z": -0.0018921894807548611
          },
          "speed": 0.3,
          "acceleration": 0.5,
          "hand_positions": [
            255,
            255,
            255,
            255,
            255,
            255
          ],
          "hand_type": null,
          "hand_side": null,
          "force_grab": null,
          "trajectory_file": null,
          "trajectory_duration": null,
          "trajectory_points": null,
          "right_joints": [
            0.1344559395742735,
            0.11450812542915934,
            -0.4121908903639273,
            -1.1901556420233455,
            -0.025510185397115137,
            -0.36078690775921274,
            -0.26987090867475416
          ],
          "right_position": {
            "x": 0.22682809194950002,
            "y": -0.358231460893664,
            "z": -0.35648125412887194
          },
          "right_euler": {
            "x": -0.6837296715680924,
            "y": -1.4047187339748977,
            "z": 0.537388252028884
          },
          "right_speed": 0.3,
          "right_acceleration": 0.5,
          "right_hand_positions": [
            255,
            255,
            255,
            255,
            255,
            255
          ],
          "right_hand_type": null,
          "gripper_position": 50,
          "gripper_torque": 50
        },
        {
          "name": "Pose_12",
          "timestamp": "2026-02-25T16:34:51.558685",
          "arm": "both",
          "pose_type": "joint",
          "joints": [
            -0.002877088578621567,
            0.01553627832455895,
            -0.0009590295262071891,
            -0.022441290913253198,
            -0.0005754177157246687,
            -0.0005754177157246687,
            -0.0005754177157246687
          ],
          "position": {
            "x": -0.0038691010889512593,
            "y": 0.2060259541872585,
            "z": -0.5794522568142493
          },
          "euler": {
            "x": -0.014983310224968816,
            "y": 0.025867169077498083,
            "z": -0.0018921894807548611
          },
          "speed": 0.3,
          "acceleration": 0.5,
          "hand_positions": [
            255,
            255,
            255,
            255,
            255,
            255
          ],
          "hand_type": null,
          "hand_side": null,
          "force_grab": null,
          "trajectory_file": null,
          "trajectory_duration": null,
          "trajectory_points": null,
          "right_joints": [
            0.028195468070496332,
            0.10223254749370447,
            -0.4624440375371943,
            -1.0846623941405351,
            -0.03011352712291071,
            -0.3596360723277634,
            -0.368459143968872
          ],
          "right_position": {
            "x": 0.25007460410885646,
            "y": -0.36228655486272227,
            "z": -0.36126614054199957
          },
          "right_euler": {
            "x": -0.26759600872107225,
            "y": -1.4406833213173242,
            "z": 0.15637806337787563
          },
          "right_speed": 0.3,
          "right_acceleration": 0.5,
          "right_hand_positions": [
            255,
            255,
            255,
            255,
            255,
            255
          ],
          "right_hand_type": null,
          "gripper_position": 49,
          "gripper_torque": 50
        },
        {
          "name": "Pose_13",
          "timestamp": "2026-02-25T16:37:32.548876",
          "arm": "both",
          "pose_type": "joint",
          "joints": [
            -0.002877088578621567,
            0.01553627832455895,
            -0.0009590295262071891,
            -0.022441290913253198,
            -0.0005754177157246687,
            -0.0005754177157246687,
            -0.0005754177157246687
          ],
          "position": {
            "x": -0.0038691010889512593,
            "y": 0.2060259541872585,
            "z": -0.5794522568142493
          },
          "euler": {
            "x": -0.014983310224968816,
            "y": 0.025867169077498083,
            "z": -0.0018921894807548611
          },
          "speed": 0.3,
          "acceleration": 0.5,
          "hand_positions": [
            255,
            255,
            255,
            255,
            255,
            255
          ],
          "hand_type": null,
          "hand_side": null,
          "force_grab": null,
          "trajectory_file": null,
          "trajectory_duration": null,
          "trajectory_points": null,
          "right_joints": [
            -0.10952117189288124,
            0.1217967498283361,
            -0.46551293202105803,
            -0.9308340581368721,
            -0.025510185397115137,
            -0.35081300068665655,
            -0.39531197070267865
          ],
          "right_position": {
            "x": 0.2856318706544612,
            "y": -0.3655626900749957,
            "z": -0.36591483258591406
          },
          "right_euler": {
            "x": 0.13302158156657595,
            "y": -1.4302064811378532,
            "z": -0.22883691866888126
          },
          "right_speed": 0.3,
          "right_acceleration": 0.5,
          "right_hand_positions": [
            255,
            255,
            255,
            255,
            255,
            255
          ],
          "right_hand_type": null,
          "gripper_position": 48,
          "gripper_torque": 50
        },
        {
          "name": "Pose_14",
          "timestamp": "2026-02-25T16:41:16.314780",
          "arm": "both",
          "pose_type": "joint",
          "joints": [
            -0.002877088578621567,
            0.01553627832455895,
            -0.0009590295262071891,
            -0.022441290913253198,
            -0.0005754177157246687,
            -0.0005754177157246687,
            -0.0005754177157246687
          ],
          "position": {
            "x": -0.0038691010889512593,
            "y": 0.2060259541872585,
            "z": -0.5794522568142493
          },
          "euler": {
            "x": -0.014983310224968816,
            "y": 0.025867169077498083,
            "z": -0.0018921894807548611
          },
          "speed": 0.3,
          "acceleration": 0.5,
          "hand_positions": [
            255,
            255,
            255,
            255,
            255,
            255
          ],
          "hand_type": null,
          "hand_side": null,
          "force_grab": null,
          "trajectory_file": null,
          "trajectory_duration": null,
          "trajectory_points": null,
          "right_joints": [
            -0.15133485923552215,
            0.10568505378805249,
            -0.4831590753032735,
            -0.8913220416571299,
            0.07384527351796777,
            -0.357718013275349,
            -0.3680755321583895
          ],
          "right_position": {
            "x": 0.29709040096945516,
            "y": -0.35883478121119416,
            "z": -0.36804875595882913
          },
          "right_euler": {
            "x": -0.189503549255536,
            "y": -1.4054329724832832,
            "z": 0.09348806660118633
          },
          "right_speed": 0.3,
          "right_acceleration": 0.5,
          "right_hand_positions": [
            255,
            255,
            255,
            255,
            255,
            255
          ],
          "right_hand_type": null,
          "gripper_position": 48,
          "gripper_torque": 50
        },
        {
          "name": "Pose_17",
          "timestamp": "2026-02-25T16:48:12.024445",
          "arm": "both",
          "pose_type": "joint",
          "joints": [
            -0.002877088578621567,
            0.01553627832455895,
            -0.0009590295262071891,
            -0.022441290913253198,
            -0.0005754177157246687,
            -0.0005754177157246687,
            -0.0005754177157246687
          ],
          "position": {
            "x": -0.0038691010889512593,
            "y": 0.2060259541872585,
            "z": -0.5794522568142493
          },
          "euler": {
            "x": -0.014983310224968816,
            "y": 0.025867169077498083,
            "z": -0.0018921894807548611
          },
          "speed": 0.3,
          "acceleration": 0.5,
          "hand_positions": [
            255,
            255,
            255,
            255,
            255,
            255
          ],
          "hand_type": null,
          "hand_side": null,
          "force_grab": null,
          "trajectory_file": null,
          "trajectory_duration": null,
          "trajectory_points": null,
          "right_joints": [
            -0.27984481574731035,
            0.10683588921950005,
            -0.4827754634927892,
            -0.7029686427100028,
            0.10952117189288124,
            -0.42868619821469345,
            -0.33777019913023665
          ],
          "right_position": {
            "x": 0.32877996457187336,
            "y": -0.3491166099141983,
            "z": -0.37172980730044924
          },
          "right_euler": {
            "x": -0.029241888723641328,
            "y": -1.41785994251348,
            "z": -0.06993462156003068
          },
          "right_speed": 0.3,
          "right_acceleration": 0.5,
          "right_hand_positions": [
            255,
            255,
            255,
            255,
            255,
            255
          ],
          "right_hand_type": null,
          "gripper_position": 47,
          "gripper_torque": 50
        },
        {
          "name": "Pose_18",
          "timestamp": "2026-02-25T16:49:28.639978",
          "arm": "both",
          "pose_type": "joint",
          "joints": [
            -0.002877088578621567,
            0.01553627832455895,
            -0.0009590295262071891,
            -0.022441290913253198,
            -0.0005754177157246687,
            -0.0005754177157246687,
            -0.0005754177157246687
          ],
          "position": {
            "x": -0.0038691010889512593,
            "y": 0.2060259541872585,
            "z": -0.5794522568142493
          },
          "euler": {
            "x": -0.014983310224968816,
            "y": 0.025867169077498083,
            "z": -0.0018921894807548611
          },
          "speed": 0.3,
          "acceleration": 0.5,
          "hand_positions": [
            255,
            255,
            255,
            255,
            255,
            255
          ],
          "hand_type": null,
          "hand_side": null,
          "force_grab": null,
          "trajectory_file": null,
          "trajectory_duration": null,
          "trajectory_points": null,
          "right_joints": [
            -0.27984481574731035,
            0.10721950102998434,
            -0.4831590753032735,
            -0.7033522545204853,
            0.10913756008239872,
            -0.42906981002517774,
            -0.33777019913023665
          ],
          "right_position": {
            "x": 0.3287676104593504,
            "y": -0.349413932289052,
            "z": -0.37152217479087507
          },
          "right_euler": {
            "x": -0.030927634468124215,
            "y": -1.4187520527226698,
            "z": -0.06894146684139758
          },
          "right_speed": 0.3,
          "right_acceleration": 0.5,
          "right_hand_positions": [
            255,
            255,
            255,
            255,
            255,
            255
          ],
          "right_hand_type": null,
          "gripper_position": 30,
          "gripper_torque": 50
        },
        {
          "name": "Pose_19",
          "timestamp": "2026-02-25T16:49:47.688053",
          "arm": "both",
          "pose_type": "joint",
          "joints": [
            -0.002877088578621567,
            0.01553627832455895,
            -0.0009590295262071891,
            -0.022441290913253198,
            -0.0005754177157246687,
            -0.0005754177157246687,
            -0.0005754177157246687
          ],
          "position": {
            "x": -0.0038691010889512593,
            "y": 0.2060259541872585,
            "z": -0.5794522568142493
          },
          "euler": {
            "x": -0.014983310224968816,
            "y": 0.025867169077498083,
            "z": -0.0018921894807548611
          },
          "speed": 0.3,
          "acceleration": 0.5,
          "hand_positions": [
            255,
            255,
            255,
            255,
            255,
            255
          ],
          "hand_type": null,
          "hand_side": null,
          "force_grab": null,
          "trajectory_file": null,
          "trajectory_duration": null,
          "trajectory_points": null,
          "right_joints": [
            -0.26181506065461235,
            0.10645227740901753,
            -0.4800901808194098,
            -0.6995161364156566,
            0.05006134126802486,
            -0.9730313572899973,
            -0.3389210345616842
          ],
          "right_position": {
            "x": 0.31256422656446536,
            "y": -0.34613028484343344,
            "z": -0.3116076302378838
          },
          "right_euler": {
            "x": -2.76768914630815,
            "y": -1.187856307095503,
            "z": 2.646921938138972
          },
          "right_speed": 0.3,
          "right_acceleration": 0.5,
          "right_hand_positions": [
            255,
            255,
            255,
            255,
            255,
            255
          ],
          "right_hand_type": null,
          "gripper_position": 29,
          "gripper_torque": 50
        }
      ],
      "created": "2026-02-25T16:17:32.079608"
    }
  ]
}